{"v":3,"stories":{"assessedby--default":{"id":"assessedby--default","name":"Default","title":"AssessedBy","importPath":"./src/assessed-by/AssessedBy.stories.tsx","tags":["story"],"kind":"AssessedBy","story":"Default","parameters":{"__id":"assessedby--default","docsOnly":false,"fileName":"./src/assessed-by/AssessedBy.stories.tsx"}},"autocomplete--autocomplete":{"id":"autocomplete--autocomplete","name":"Autocomplete","title":"Autocomplete","importPath":"./src/autocomplete/Autocomplete.stories.tsx","tags":["story"],"kind":"Autocomplete","story":"Autocomplete","parameters":{"__id":"autocomplete--autocomplete","docsOnly":false,"fileName":"./src/autocomplete/Autocomplete.stories.tsx"}},"basiclist--basic-list":{"id":"basiclist--basic-list","name":"Basic List","title":"BasicList","importPath":"./src/basic-list/BasicList.stories.tsx","tags":["story"],"kind":"BasicList","story":"Basic List","parameters":{"__id":"basiclist--basic-list","docsOnly":false,"fileName":"./src/basic-list/BasicList.stories.tsx"}},"box--box-component":{"id":"box--box-component","name":"Box Component","title":"Box","importPath":"./src/box/Box.stories.tsx","tags":["story"],"kind":"Box","story":"Box Component","parameters":{"__id":"box--box-component","docsOnly":false,"fileName":"./src/box/Box.stories.tsx"}},"content-with-tooltip--tooltip":{"id":"content-with-tooltip--tooltip","name":"Tooltip","title":"Content with tooltip","importPath":"./src/content-with-tooltip/ContentWithTooltip.stories.tsx","tags":["story"],"kind":"Content with tooltip","story":"Tooltip","parameters":{"__id":"content-with-tooltip--tooltip","docsOnly":false,"fileName":"./src/content-with-tooltip/ContentWithTooltip.stories.tsx"}},"detail-view--detail-view":{"id":"detail-view--detail-view","name":"Detail View","title":"Detail view","importPath":"./src/detail-view/DetailView.stories.tsx","tags":["story"],"kind":"Detail view","story":"Detail View","parameters":{"__id":"detail-view--detail-view","docsOnly":false,"fileName":"./src/detail-view/DetailView.stories.tsx"}},"expandable-panel--expandable-panel":{"id":"expandable-panel--expandable-panel","name":"Expandable Panel","title":"Expandable panel","importPath":"./src/expandable-panel/ExpandablePanel.stories.tsx","tags":["story"],"kind":"Expandable panel","story":"Expandable Panel","parameters":{"__id":"expandable-panel--expandable-panel","docsOnly":false,"fileName":"./src/expandable-panel/ExpandablePanel.stories.tsx"}},"header--default":{"id":"header--default","name":"Default","title":"Header","importPath":"./src/header/Header.stories.tsx","tags":["story"],"kind":"Header","story":"Default","parameters":{"__id":"header--default","docsOnly":false,"fileName":"./src/header/Header.stories.tsx"}},"info-panel--info-panel":{"id":"info-panel--info-panel","name":"Info Panel","title":"Info panel","importPath":"./src/info-panel/InfoPanel.stories.tsx","tags":["story"],"kind":"Info panel","story":"Info Panel","parameters":{"__id":"info-panel--info-panel","docsOnly":false,"fileName":"./src/info-panel/InfoPanel.stories.tsx"}},"labelled-content--labelled-content":{"id":"labelled-content--labelled-content","name":"Labelled Content","title":"Labelled content","importPath":"./src/labelled-content/LabelledContent.stories.tsx","tags":["story"],"kind":"Labelled content","story":"Labelled Content","parameters":{"__id":"labelled-content--labelled-content","docsOnly":false,"fileName":"./src/labelled-content/LabelledContent.stories.tsx"}},"link-button--link-button":{"id":"link-button--link-button","name":"Link Button","title":"Link button","importPath":"./src/link-button/LinkButton.stories.tsx","tags":["story"],"kind":"Link button","story":"Link Button","parameters":{"__id":"link-button--link-button","docsOnly":false,"fileName":"./src/link-button/LinkButton.stories.tsx"}},"navigation-with-detail--navigation-with-detail":{"id":"navigation-with-detail--navigation-with-detail","name":"Navigation With Detail","title":"Navigation with detail","importPath":"./src/navigation-with-detail-view/NavigationWithDetailView.stories.tsx","tags":["story"],"kind":"Navigation with detail","story":"Navigation With Detail","parameters":{"__id":"navigation-with-detail--navigation-with-detail","docsOnly":false,"fileName":"./src/navigation-with-detail-view/NavigationWithDetailView.stories.tsx"}},"period-list--perioder":{"id":"period-list--perioder","name":"Perioder","title":"Period list","importPath":"./src/period-list/PeriodList.stories.tsx","tags":["story"],"kind":"Period list","story":"Perioder","parameters":{"__id":"period-list--perioder","docsOnly":false,"fileName":"./src/period-list/PeriodList.stories.tsx"}},"person-card--person-card":{"id":"person-card--person-card","name":"Person Card","title":"Person card","importPath":"./src/person-card/PersonCard.stories.tsx","tags":["story"],"kind":"Person card","story":"Person Card","parameters":{"__id":"person-card--person-card","docsOnly":false,"fileName":"./src/person-card/PersonCard.stories.tsx"}},"process-menu--state-from-props":{"id":"process-menu--state-from-props","name":"State From Props","title":"Process menu","importPath":"./src/process-menu/ProcessMenu.stories.tsx","tags":["story"],"kind":"Process menu","story":"State From Props","parameters":{"__id":"process-menu--state-from-props","docsOnly":false,"fileName":"./src/process-menu/ProcessMenu.stories.tsx"}},"process-menu--stateful":{"id":"process-menu--stateful","name":"Stateful","title":"Process menu","importPath":"./src/process-menu/ProcessMenu.stories.tsx","tags":["story"],"kind":"Process menu","story":"Stateful","parameters":{"__id":"process-menu--stateful","docsOnly":false,"fileName":"./src/process-menu/ProcessMenu.stories.tsx"}},"process-menu--many-steps":{"id":"process-menu--many-steps","name":"Many Steps","title":"Process menu","importPath":"./src/process-menu/ProcessMenu.stories.tsx","tags":["story"],"kind":"Process menu","story":"Many Steps","parameters":{"__id":"process-menu--many-steps","docsOnly":false,"fileName":"./src/process-menu/ProcessMenu.stories.tsx"}},"side-menu--stateful-side-menu":{"id":"side-menu--stateful-side-menu","name":"Stateful Side Menu","title":"Side menu","importPath":"./src/side-menu/SideMenu.stories.tsx","tags":["story"],"kind":"Side menu","story":"Stateful Side Menu","parameters":{"__id":"side-menu--stateful-side-menu","docsOnly":false,"fileName":"./src/side-menu/SideMenu.stories.tsx"}},"system-button--system-button":{"id":"system-button--system-button","name":"System Button","title":"System button","importPath":"./src/system-button/SystemButton.stories.tsx","tags":["story"],"kind":"System button","story":"System Button","parameters":{"__id":"system-button--system-button","docsOnly":false,"fileName":"./src/system-button/SystemButton.stories.tsx"}},"title-with-underline--title-with-underline":{"id":"title-with-underline--title-with-underline","name":"Title With Underline","title":"Title with underline","importPath":"./src/title-with-underline/TitleWithUnderline.stories.tsx","tags":["story"],"kind":"Title with underline","story":"Title With Underline","parameters":{"__id":"title-with-underline--title-with-underline","docsOnly":false,"fileName":"./src/title-with-underline/TitleWithUnderline.stories.tsx"}},"userpanel--default":{"id":"userpanel--default","name":"Default","title":"UserPanel","importPath":"./src/user-panel/UserPanel.stories.tsx","tags":["story"],"kind":"UserPanel","story":"Default","parameters":{"__id":"userpanel--default","docsOnly":false,"fileName":"./src/user-panel/UserPanel.stories.tsx"}}}}
